eve_pytorch/__init__.py
eve_pytorch/data.py
eve_pytorch/eve_pytorch.py
eve_pytorch/train.py
eve_pytorch-0.0.5.dist-info/METADATA
eve_pytorch-0.0.5.dist-info/WHEEL
eve_pytorch-0.0.5.dist-info/top_level.txt
eve_pytorch-0.0.5.dist-info/RECORD
